[{"macro": "Play / Stop", "val": [17, 18, 80], "param": null, "param_enabled": false, "action": "play_stop"}, {"macro": "Load File 1", "val": [17, 18, 49], "param": "threed.gwm", "param_enabled": true, "action": "load_file"}, {"macro": "Load File 2", "val": [17, 18, 50], "param": "eb_eight_melodies.gwm", "param_enabled": true, "action": "load_file"}, {"macro": "Load File 3", "val": [17, 18, 51], "param": "aot_theme_1.gwm", "param_enabled": true, "action": "load_file"}, {"macro": "Load File 4", "val": [17, 18, 52], "param": "ut_determination.gwm", "param_enabled": true, "action": "load_file"}]